ontolearner/VERSION
ontolearner/__init__.py
ontolearner/_learner.py
ontolearner/_ontology.py
ontolearner/base/__init__.py
ontolearner/base/learner.py
ontolearner/base/ontology.py
ontolearner/base/text2onto.py
ontolearner/data_structure/__init__.py
ontolearner/data_structure/data.py
ontolearner/data_structure/metric.py
ontolearner/evaluation/__init__.py
ontolearner/evaluation/evaluate.py
ontolearner/evaluation/metrics.py
ontolearner/learner/__init__.py
ontolearner/learner/label_mapper.py
ontolearner/learner/llm.py
ontolearner/learner/prompt.py
ontolearner/learner/rag/__init__.py
ontolearner/learner/rag/rag.py
ontolearner/learner/retriever/__init__.py
ontolearner/learner/retriever/augmented_retriever.py
ontolearner/learner/retriever/crossencoder.py
ontolearner/learner/retriever/embedding.py
ontolearner/learner/retriever/learner.py
ontolearner/learner/retriever/ngram.py
ontolearner/learner/taxonomy_discovery/__init__.py
ontolearner/learner/taxonomy_discovery/alexbek.py
ontolearner/learner/taxonomy_discovery/rwthdbis.py
ontolearner/learner/taxonomy_discovery/sbunlp.py
ontolearner/learner/taxonomy_discovery/skhnlp.py
ontolearner/learner/term_typing/__init__.py
ontolearner/learner/term_typing/alexbek.py
ontolearner/learner/term_typing/rwthdbis.py
ontolearner/learner/term_typing/sbunlp.py
ontolearner/learner/text2onto/__init__.py
ontolearner/learner/text2onto/alexbek.py
ontolearner/learner/text2onto/sbunlp.py
ontolearner/ontology/__init__.py
ontolearner/ontology/agriculture.py
ontolearner/ontology/arts_humanities.py
ontolearner/ontology/biology.py
ontolearner/ontology/chemistry.py
ontolearner/ontology/ecology_environment.py
ontolearner/ontology/education.py
ontolearner/ontology/events.py
ontolearner/ontology/finance.py
ontolearner/ontology/food_beverage.py
ontolearner/ontology/general.py
ontolearner/ontology/geography.py
ontolearner/ontology/industry.py
ontolearner/ontology/law.py
ontolearner/ontology/library_cultural_heritage.py
ontolearner-1.4.11.dist-info/METADATA
ontolearner-1.4.11.dist-info/WHEEL
ontolearner-1.4.11.dist-info/licenses/LICENSE
ontolearner-1.4.11.dist-info/RECORD
