Metadata-Version: 2.4
Name: OntoLearner
Version: 1.4.11
Summary: OntoLearner: A Modular Python Library for Ontology Learning with LLMs.
License: MIT
License-File: LICENSE
Author: Hamed Babaei Giglou
Author-email: hamedbabaeigiglou@gmail.com
Requires-Python: >=3.10,<3.14.0
Classifier: License :: OSI Approved :: MIT License
Classifier: Programming Language :: Python :: 3
Classifier: Programming Language :: Python :: 3.10
Classifier: Programming Language :: Python :: 3.11
Classifier: Programming Language :: Python :: 3.12
Classifier: Programming Language :: Python :: 3.13
Requires-Dist: Levenshtein
Requires-Dist: bitsandbytes (>=0.45.1,<1.0.0) ; platform_system == "Linux"
Requires-Dist: dspy (>=2.6.14,<3.0.0)
Requires-Dist: g4f
Requires-Dist: gensim
Requires-Dist: huggingface-hub (>=0.34.4,<0.35.0)
Requires-Dist: matplotlib
Requires-Dist: mistral-common[sentencepiece] (>=1.8.5,<2.0.0)
Requires-Dist: networkx (==3.2.1)
Requires-Dist: numpy
Requires-Dist: openpyxl
Requires-Dist: pandas
Requires-Dist: pathlib (==1.0.1)
Requires-Dist: protobuf (<5)
Requires-Dist: pydantic (==2.11.3)
Requires-Dist: python-dotenv
Requires-Dist: rdflib (==7.1.1)
Requires-Dist: scikit-learn
Requires-Dist: seaborn
Requires-Dist: sentence-transformers (>=5.1.0,<6.0.0)
Requires-Dist: torch (>=2.8.0,<3.0.0)
Requires-Dist: tqdm
Requires-Dist: transformers (>=4.56.0,<5.0.0)
Project-URL: Homepage, https://ontolearner.readthedocs.io/
Project-URL: Repository, https://github.com/sciknoworg/OntoLearner/
